numsolve.py
numsolve-0.0.3.dist-info/LICENSE
numsolve-0.0.3.dist-info/METADATA
numsolve-0.0.3.dist-info/WHEEL
numsolve-0.0.3.dist-info/top_level.txt
numsolve-0.0.3.dist-info/RECORD
