Metadata-Version: 2.1
Name: numsolve
Version: 0.0.3
Summary: Numerical Methods to solve various equation
Home-page: UNKNOWN
Author: Harshal Dupare
Author-email: <harshal3hd@gmail.com>
License: UNKNOWN
Keywords: python,numerical methods,equation solver
Platform: UNKNOWN
Classifier: Development Status :: 1 - Planning
Classifier: Intended Audience :: Developers
Classifier: Programming Language :: Python :: 3
Classifier: Operating System :: Unix
Classifier: Operating System :: MacOS :: MacOS X
Classifier: Operating System :: Microsoft :: Windows
Requires-Python: >=3.6
License-File: LICENSE
Requires-Dist: numpy
